tkinterie/__init__.py
tkinterie/tkinterIE.py
tkinterie-1.5.0.dist-info/LICENSE.txt
tkinterie-1.5.0.dist-info/METADATA
tkinterie-1.5.0.dist-info/WHEEL
tkinterie-1.5.0.dist-info/top_level.txt
tkinterie-1.5.0.dist-info/RECORD
