Metadata-Version: 2.1
Name: tkinterie
Version: 1.5.0
Summary: tkinter-WebView widget, based on InternetExplorer.Application
Home-page: UNKNOWN
Author: Smart-Space
Author-email: smart-space@qq.com
License: MIT License
Platform: UNKNOWN
Classifier: Intended Audience :: Developers
Classifier: Operating System :: Microsoft :: Windows
Classifier: Natural Language :: Chinese (Simplified)
Classifier: Programming Language :: Python
Classifier: Programming Language :: Python :: 3
Classifier: License :: OSI Approved :: MIT License
Classifier: Topic :: Software Development :: Libraries
Requires-Python: >=3.5
License-File: LICENSE.txt
Requires-Dist: pythonnet
